README.md
requirements.txt
setup.py
rtrace/__init__.py
rtrace/rtrace.py
rtrace.egg-info/PKG-INFO
rtrace.egg-info/SOURCES.txt
rtrace.egg-info/dependency_links.txt
rtrace.egg-info/requires.txt
rtrace.egg-info/top_level.txt
test/test_rtrace.py