Metadata-Version: 2.1
Name: rtrace
Version: 0.0.1
Summary: A few functions for ray tracing in python
Home-page: https://github.com/gmagno/rtrace
Author: gmagno
Author-email: goncalo.magno@gmail.com
License: UNKNOWN
Project-URL: Bug Reports, https://github.com/gmagno/rtrace/issues
Project-URL: Source, https://github.com/gmagno/rtrace
Keywords: ray tracing python numpy
Platform: UNKNOWN
Classifier: Development Status :: 3 - Alpha
Classifier: Intended Audience :: Developers
Classifier: License :: OSI Approved :: MIT License
Classifier: Topic :: Scientific/Engineering
Classifier: Programming Language :: Python :: 3
